DESCRIPTION.rst
LICENSE.txt
MANIFEST.in
README.rst
requirements.txt
setup.cfg
setup.py
rewind/__init__.py
rewind.egg-info/PKG-INFO
rewind.egg-info/SOURCES.txt
rewind.egg-info/dependency_links.txt
rewind.egg-info/entry_points.txt
rewind.egg-info/namespace_packages.txt
rewind.egg-info/requires.txt
rewind.egg-info/top_level.txt
rewind/server/__init__.py
rewind/server/config.py
rewind/server/eventstores.py
rewind/server/main.py
rewind/server/test/__init__.py
rewind/server/test/test_code.py
rewind/server/test/test_config.py
rewind/server/test/test_eventstores.py
rewind/server/test/test_main.py