Metadata-Version: 1.0
Name: rewind
Version: 0.3.1
Summary: Rewind is a (CQRS) event store that talks ZeroMQ.
Home-page: https://github.com/JensRantil/rewind
Author: Jens Rantil
Author-email: jens.rantil@gmail.com
License: GNU AGPL, version 3
Keywords: CQRS,event sourcing,ZeroMQ
Platform: UNKNOWN
Classifier: Development Status :: 4 - Beta
Classifier: Environment :: No Input/Output (Daemon)
Classifier: Intended Audience :: Other Audience
Classifier: License :: OSI Approved :: GNU Affero General Public License v3
Classifier: Natural Language :: English
Classifier: Operating System :: OS Independent
Classifier: Programming Language :: Python :: 2.7
Classifier: Programming Language :: Python :: 3.2
Classifier: Topic :: Database :: Database Engines/Servers
Classifier: Topic :: Software Development :: Object Brokering
Classifier: Topic :: System :: Distributed Computing
